{
    "formOptions":[
        {
            "label":"Name",
            "id":"name",
            "type":"text",
            "placeholder":"Your Name"
        },
        {
            "label":"Email",
            "id":"email",
            "type":"email",
            "placeholder":"Email id"
        },
        {
            "label":"Phone",
            "id":"phone",
            "type":"text",
            "placeholder":"Phone no"
        },
        {
            "label":"Subject",
            "id":"subject",
            "type":"text",
            "placeholder":"Your Subject"
        },
        {
            "label":"Message",
            "id":"message",
            "type":"text",
            "placeholder":"How can we help you?"
        }
    ]
}